playwrightgym/__init__.py
playwrightgym/playwright_env.py
playwrightgym/__pycache__/__init__.cpython-38.pyc
playwrightgym/__pycache__/playwright_env.cpython-38.pyc
playwrightgym/webtasks/login-user.html
playwrightgym-0.1.0.dist-info/METADATA
playwrightgym-0.1.0.dist-info/WHEEL
playwrightgym-0.1.0.dist-info/top_level.txt
playwrightgym-0.1.0.dist-info/RECORD
