Metadata-Version: 2.1
Name: playwrightgym
Version: 0.1.0
Summary: Deep Reinforcement Learning Environments for web-based tasks using Playwright
Home-page: https://github.com/praveen-palanisamy/playwrightgym
Author: Praveen Palanisamy
Author-email: praveen.palanisamy@outlook.com
License: UNKNOWN
Project-URL: Source, https://github.com/praveen-palanisamy/playwrightgym
Project-URL: Author website, https://praveenp.com
Keywords: playwright gym,rl web tasks,rl web navigation,rl in browser,Gym environments
Platform: UNKNOWN
Classifier: Development Status :: 2 - Pre-Alpha
Classifier: Intended Audience :: Science/Research
Classifier: Intended Audience :: Developers
Classifier: Intended Audience :: Education
Classifier: Topic :: Scientific/Engineering
Classifier: Topic :: Scientific/Engineering :: Artificial Intelligence
Classifier: License :: OSI Approved :: MIT License
Classifier: Programming Language :: Python :: 3
Classifier: Programming Language :: Python :: 3.7
Classifier: Programming Language :: Python :: 3.8
Classifier: Programming Language :: Python :: 3.9
Classifier: Programming Language :: Python :: 3 :: Only
Requires-Python: >=3.7, <4
Requires-Dist: gym
